nothrottling_dl/__init__.py
nothrottling_dl/nothrottling_dl.py
nothrottling_dl-0.1.5.dist-info/entry_points.txt
nothrottling_dl-0.1.5.dist-info/LICENSE
nothrottling_dl-0.1.5.dist-info/WHEEL
nothrottling_dl-0.1.5.dist-info/METADATA
nothrottling_dl-0.1.5.dist-info/RECORD
